{
  "hello": "Hello World!",
  "primary_color": "Primary Color",
  "secondary_color": "Secondary Color",
  "tertiary_color": "Tertiary Color",
  "text_color": "Text Color",
  "theme_color": "Theme Color",
  "body_typography": "Body Typography",
  "font_size": "Font Size (in px)",
  "line_height": "Line Height (in px)",
  "layout_switcher": "Layout Switcher",
  "layout_style": "Layout Style",
  "wide": "Wide",
  "boxed": "Boxed",
  "header_switcher": "Header Switcher",
  "theme": "Theme",
  "dark": "Dark",
  "light": "Light",
  "alignment": "Alignment",
  "left": "Left",
  "center": "Center",
  "right": "Right",
  "contact_button": "Contact Button",
  "theme_fonts": "Theme Fonts",
  "without": "Without",
  "rules": "CSS rules to specify families (Without 'font-family:' )",
  "select_from": "Select from"
}
